{
	"credit": "Made with Blockbench",
	"texture_size": [64, 64],
	"textures": {
		"0": "piece_craft:item/sube_sube_no_mi_3d",
		"particle": "piece_craft:item/sube_sube_no_mi_3d"
	},
	"elements": [
		{
			"from": [2.6, 2, 6],
			"to": [3.6, 8, 11],
			"rotation": {"angle": 0, "axis": "y", "origin": [4.6, 2, 6]},
			"faces": {
				"north": {"uv": [12.25, 12.25, 12.5, 13.75], "texture": "#0"},
				"east": {"uv": [11, 12.25, 12.25, 13.75], "texture": "#0"},
				"south": {"uv": [13.75, 12.25, 14, 13.75], "texture": "#0"},
				"west": {"uv": [12.5, 12.25, 13.75, 13.75], "texture": "#0"},
				"up": {"uv": [12.5, 12.25, 12.25, 11], "texture": "#0"},
				"down": {"uv": [12.75, 11, 12.5, 12.25], "texture": "#0"}
			}
		},
		{
			"from": [7, 1, 6],
			"to": [9, 9, 11],
			"rotation": {"angle": 0, "axis": "y", "origin": [9, 1, 6]},
			"faces": {
				"north": {"uv": [5.75, 11.75, 6.25, 13.75], "texture": "#0"},
				"east": {"uv": [4.5, 11.75, 5.75, 13.75], "texture": "#0"},
				"south": {"uv": [7.5, 11.75, 8, 13.75], "texture": "#0"},
				"west": {"uv": [6.25, 11.75, 7.5, 13.75], "texture": "#0"},
				"up": {"uv": [6.25, 11.75, 5.75, 10.5], "texture": "#0"},
				"down": {"uv": [6.75, 10.5, 6.25, 11.75], "texture": "#0"}
			}
		},
		{
			"from": [3.3, 1, 6],
			"to": [5.3, 9, 11],
			"rotation": {"angle": 0, "axis": "y", "origin": [5.3, 1, 6]},
			"faces": {
				"north": {"uv": [10.25, 9, 10.75, 11], "texture": "#0"},
				"east": {"uv": [9, 9, 10.25, 11], "texture": "#0"},
				"south": {"uv": [12, 9, 12.5, 11], "texture": "#0"},
				"west": {"uv": [10.75, 9, 12, 11], "texture": "#0"},
				"up": {"uv": [10.75, 9, 10.25, 7.75], "texture": "#0"},
				"down": {"uv": [11.25, 7.75, 10.75, 9], "texture": "#0"}
			}
		},
		{
			"from": [5, 0, 5],
			"to": [7, 10, 12],
			"rotation": {"angle": 0, "axis": "y", "origin": [7, 0, 5]},
			"faces": {
				"north": {"uv": [1.75, 6.25, 2.25, 8.75], "texture": "#0"},
				"east": {"uv": [0, 6.25, 1.75, 8.75], "texture": "#0"},
				"south": {"uv": [4, 6.25, 4.5, 8.75], "texture": "#0"},
				"west": {"uv": [2.25, 6.25, 4, 8.75], "texture": "#0"},
				"up": {"uv": [2.25, 6.25, 1.75, 4.5], "texture": "#0"},
				"down": {"uv": [2.75, 4.5, 2.25, 6.25], "texture": "#0"}
			}
		},
		{
			"from": [9, 0, 5],
			"to": [11, 10, 12],
			"rotation": {"angle": 0, "axis": "y", "origin": [9, 0, 5]},
			"faces": {
				"north": {"uv": [2.25, 6.25, 1.75, 8.75], "texture": "#0"},
				"east": {"uv": [4, 6.25, 2.25, 8.75], "texture": "#0"},
				"south": {"uv": [4.5, 6.25, 4, 8.75], "texture": "#0"},
				"west": {"uv": [1.75, 6.25, 0, 8.75], "texture": "#0"},
				"up": {"uv": [1.75, 6.25, 2.25, 4.5], "texture": "#0"},
				"down": {"uv": [2.25, 4.5, 2.75, 6.25], "texture": "#0"}
			}
		},
		{
			"from": [9, 1, 4],
			"to": [11, 9, 13],
			"rotation": {"angle": 0, "axis": "y", "origin": [9, 1, 4]},
			"faces": {
				"north": {"uv": [6, 4.25, 5.5, 6.25], "texture": "#0"},
				"east": {"uv": [8.25, 4.25, 6, 6.25], "texture": "#0"},
				"south": {"uv": [8.75, 4.25, 8.25, 6.25], "texture": "#0"},
				"west": {"uv": [5.5, 4.25, 3.25, 6.25], "texture": "#0"},
				"up": {"uv": [5.5, 4.25, 6, 2], "texture": "#0"},
				"down": {"uv": [6, 2, 6.5, 4.25], "texture": "#0"}
			}
		},
		{
			"from": [5, 1, 4],
			"to": [7, 9, 13],
			"rotation": {"angle": 0, "axis": "y", "origin": [7, 1, 4]},
			"faces": {
				"north": {"uv": [5.5, 4.25, 6, 6.25], "texture": "#0"},
				"east": {"uv": [3.25, 4.25, 5.5, 6.25], "texture": "#0"},
				"south": {"uv": [8.25, 4.25, 8.75, 6.25], "texture": "#0"},
				"west": {"uv": [6, 4.25, 8.25, 6.25], "texture": "#0"},
				"up": {"uv": [6, 4.25, 5.5, 2], "texture": "#0"},
				"down": {"uv": [6.5, 2, 6, 4.25], "texture": "#0"}
			}
		},
		{
			"from": [12.4, 2, 6],
			"to": [13.4, 8, 11],
			"rotation": {"angle": 0, "axis": "y", "origin": [11.4, 2, 6]},
			"faces": {
				"north": {"uv": [12.5, 12.25, 12.25, 13.75], "texture": "#0"},
				"east": {"uv": [13.75, 12.25, 12.5, 13.75], "texture": "#0"},
				"south": {"uv": [14, 12.25, 13.75, 13.75], "texture": "#0"},
				"west": {"uv": [12.25, 12.25, 11, 13.75], "texture": "#0"},
				"up": {"uv": [12.25, 12.25, 12.5, 11], "texture": "#0"},
				"down": {"uv": [12.5, 11, 12.75, 12.25], "texture": "#0"}
			}
		},
		{
			"from": [10.7, 1, 6],
			"to": [12.7, 9, 11],
			"rotation": {"angle": 0, "axis": "y", "origin": [10.7, 1, 6]},
			"faces": {
				"north": {"uv": [10.75, 9, 10.25, 11], "texture": "#0"},
				"east": {"uv": [12, 9, 10.75, 11], "texture": "#0"},
				"south": {"uv": [12.5, 9, 12, 11], "texture": "#0"},
				"west": {"uv": [10.25, 9, 9, 11], "texture": "#0"},
				"up": {"uv": [10.25, 9, 10.75, 7.75], "texture": "#0"},
				"down": {"uv": [10.75, 7.75, 11.25, 9], "texture": "#0"}
			}
		},
		{
			"from": [3.3, 2, 5],
			"to": [5.3, 8, 12],
			"rotation": {"angle": 0, "axis": "y", "origin": [5.3, 2, 5]},
			"faces": {
				"north": {"uv": [9, 6.25, 9.5, 7.75], "texture": "#0"},
				"east": {"uv": [7.25, 6.25, 9, 7.75], "texture": "#0"},
				"south": {"uv": [11.25, 6.25, 11.75, 7.75], "texture": "#0"},
				"west": {"uv": [9.5, 6.25, 11.25, 7.75], "texture": "#0"},
				"up": {"uv": [9.5, 6.25, 9, 4.5], "texture": "#0"},
				"down": {"uv": [10, 4.5, 9.5, 6.25], "texture": "#0"}
			}
		},
		{
			"from": [10.7, 2, 5],
			"to": [12.7, 8, 12],
			"rotation": {"angle": 0, "axis": "y", "origin": [10.7, 2, 5]},
			"faces": {
				"north": {"uv": [9.5, 6.25, 9, 7.75], "texture": "#0"},
				"east": {"uv": [11.25, 6.25, 9.5, 7.75], "texture": "#0"},
				"south": {"uv": [11.75, 6.25, 11.25, 7.75], "texture": "#0"},
				"west": {"uv": [9, 6.25, 7.25, 7.75], "texture": "#0"},
				"up": {"uv": [9, 6.25, 9.5, 4.5], "texture": "#0"},
				"down": {"uv": [9.5, 4.5, 10, 6.25], "texture": "#0"}
			}
		},
		{
			"from": [7, 2, 5],
			"to": [9, 8, 12],
			"rotation": {"angle": 0, "axis": "y", "origin": [9, 2, 5]},
			"faces": {
				"north": {"uv": [8.25, 1.75, 8.75, 3.25], "texture": "#0"},
				"east": {"uv": [6.5, 1.75, 8.25, 3.25], "texture": "#0"},
				"south": {"uv": [10.5, 1.75, 11, 3.25], "texture": "#0"},
				"west": {"uv": [8.75, 1.75, 10.5, 3.25], "texture": "#0"},
				"up": {"uv": [8.75, 1.75, 8.25, 0], "texture": "#0"},
				"down": {"uv": [9.25, 0, 8.75, 1.75], "texture": "#0"}
			}
		},
		{
			"from": [7, 8, 7],
			"to": [9, 11, 9],
			"rotation": {"angle": -22.5, "axis": "x", "origin": [7, 8, 7]},
			"faces": {
				"north": {"uv": [0.5, 0.5, 1, 1.25], "texture": "#0"},
				"east": {"uv": [0, 0.5, 0.5, 1.25], "texture": "#0"},
				"south": {"uv": [1.5, 0.5, 2, 1.25], "texture": "#0"},
				"west": {"uv": [1, 0.5, 1.5, 1.25], "texture": "#0"},
				"up": {"uv": [1, 0.5, 0.5, 0], "texture": "#0"},
				"down": {"uv": [1.5, 0, 1, 0.5], "texture": "#0"}
			}
		},
		{
			"from": [7.5, 11, 6.3],
			"to": [8.5, 14, 7.3],
			"rotation": {"angle": 0, "axis": "y", "origin": [6.02112, 14.3, 6.15067]},
			"faces": {
				"north": {"uv": [0.25, 1.5, 0.5, 2.25], "texture": "#0"},
				"east": {"uv": [0, 1.5, 0.25, 2.25], "texture": "#0"},
				"south": {"uv": [0.75, 1.5, 1, 2.25], "texture": "#0"},
				"west": {"uv": [0.5, 1.5, 0.75, 2.25], "texture": "#0"},
				"up": {"uv": [0.5, 1.5, 0.25, 1.25], "texture": "#0"},
				"down": {"uv": [0.75, 1.25, 0.5, 1.5], "texture": "#0"}
			}
		},
		{
			"from": [4.63739, 13.9, 5.47835],
			"to": [11.63739, 14.9, 6.47835],
			"rotation": {"angle": -22.5, "axis": "y", "origin": [6.02112, 14.3, 6.15067]},
			"faces": {
				"north": {"uv": [3.5, 0.25, 5.25, 0.5], "texture": "#0"},
				"east": {"uv": [3.25, 0.25, 3.5, 0.5], "texture": "#0"},
				"south": {"uv": [5.5, 0.25, 7.25, 0.5], "texture": "#0"},
				"west": {"uv": [5.25, 0.25, 5.5, 0.5], "texture": "#0"},
				"up": {"uv": [5.25, 0.25, 3.5, 0], "texture": "#0"},
				"down": {"uv": [7, 0, 5.25, 0.25], "texture": "#0"}
			}
		},
		{
			"from": [4.24463, 14.02982, 5.1],
			"to": [5.24463, 15.02982, 6.1],
			"rotation": {"angle": 45, "axis": "z", "origin": [4.74463, 14.52982, 5.6]},
			"faces": {
				"north": {"uv": [4.25, 1.5, 4.5, 1.75], "texture": "#0"},
				"east": {"uv": [4, 1.5, 4.25, 1.75], "texture": "#0"},
				"south": {"uv": [4.75, 1.5, 5, 1.75], "texture": "#0"},
				"west": {"uv": [4.5, 1.5, 4.75, 1.75], "texture": "#0"},
				"up": {"uv": [4.5, 1.5, 4.25, 1.25], "texture": "#0"},
				"down": {"uv": [4.75, 1.25, 4.5, 1.5], "texture": "#0"}
			}
		},
		{
			"from": [4.36621, 13.49026, 5.1],
			"to": [5.36621, 14.49026, 6.1],
			"rotation": {"angle": 45, "axis": "z", "origin": [4.86621, 13.99026, 5.6]},
			"faces": {
				"north": {"uv": [4.25, 1, 4.5, 1.25], "texture": "#0"},
				"east": {"uv": [4, 1, 4.25, 1.25], "texture": "#0"},
				"south": {"uv": [4.75, 1, 5, 1.25], "texture": "#0"},
				"west": {"uv": [4.5, 1, 4.75, 1.25], "texture": "#0"},
				"up": {"uv": [4.5, 1, 4.25, 0.75], "texture": "#0"},
				"down": {"uv": [4.75, 0.75, 4.5, 1], "texture": "#0"}
			}
		},
		{
			"from": [4.2287, 12.95598, 5.2],
			"to": [5.2287, 13.95598, 6.2],
			"rotation": {"angle": 0, "axis": "y", "origin": [4.7287, 13.45598, 5.7]},
			"faces": {
				"north": {"uv": [3.5, 1.75, 3.75, 2], "texture": "#0"},
				"east": {"uv": [3.25, 1.75, 3.5, 2], "texture": "#0"},
				"south": {"uv": [4, 1.75, 4.25, 2], "texture": "#0"},
				"west": {"uv": [3.75, 1.75, 4, 2], "texture": "#0"},
				"up": {"uv": [3.75, 1.75, 3.5, 1.5], "texture": "#0"},
				"down": {"uv": [4, 1.5, 3.75, 1.75], "texture": "#0"}
			}
		},
		{
			"from": [4.35425, 12.16327, 5.3],
			"to": [5.35425, 13.16327, 6.3],
			"rotation": {"angle": -45, "axis": "z", "origin": [5.09836, 12.79519, 5.85]},
			"faces": {
				"north": {"uv": [0.25, 4.5, 0.5, 4.75], "texture": "#0"},
				"east": {"uv": [0, 4.5, 0.25, 4.75], "texture": "#0"},
				"south": {"uv": [0.75, 4.5, 1, 4.75], "texture": "#0"},
				"west": {"uv": [0.5, 4.5, 0.75, 4.75], "texture": "#0"},
				"up": {"uv": [0.5, 4.5, 0.25, 4.25], "texture": "#0"},
				"down": {"uv": [0.75, 4.25, 0.5, 4.5], "texture": "#0"}
			}
		},
		{
			"from": [4.86425, 12.21586, 5.4],
			"to": [5.86425, 13.21586, 6.4],
			"rotation": {"angle": 0, "axis": "y", "origin": [5.09836, 12.79519, 5.85]},
			"faces": {
				"north": {"uv": [4.25, 2, 4.5, 2.25], "texture": "#0"},
				"east": {"uv": [4, 2, 4.25, 2.25], "texture": "#0"},
				"south": {"uv": [4.75, 2, 5, 2.25], "texture": "#0"},
				"west": {"uv": [4.5, 2, 4.75, 2.25], "texture": "#0"},
				"up": {"uv": [4.5, 2, 4.25, 1.75], "texture": "#0"},
				"down": {"uv": [4.75, 1.75, 4.5, 2], "texture": "#0"}
			}
		},
		{
			"from": [4.72756, 15.56042, 5.4],
			"to": [5.72756, 16.56042, 6.4],
			"rotation": {"angle": -22.5, "axis": "z", "origin": [5.22756, 16.06042, 5.9]},
			"faces": {
				"north": {"uv": [1.25, 2, 1.5, 2.25], "texture": "#0"},
				"east": {"uv": [1, 2, 1.25, 2.25], "texture": "#0"},
				"south": {"uv": [1.75, 2, 2, 2.25], "texture": "#0"},
				"west": {"uv": [1.5, 2, 1.75, 2.25], "texture": "#0"},
				"up": {"uv": [1.5, 2, 1.25, 1.75], "texture": "#0"},
				"down": {"uv": [1.75, 1.75, 1.5, 2], "texture": "#0"}
			}
		},
		{
			"from": [5.3, 15.2, 5.5],
			"to": [6.3, 16.2, 6.5],
			"rotation": {"angle": -45, "axis": "z", "origin": [5.8, 15.7, 6]},
			"faces": {
				"north": {"uv": [1.25, 1.5, 1.5, 1.75], "texture": "#0"},
				"east": {"uv": [1, 1.5, 1.25, 1.75], "texture": "#0"},
				"south": {"uv": [1.75, 1.5, 2, 1.75], "texture": "#0"},
				"west": {"uv": [1.5, 1.5, 1.75, 1.75], "texture": "#0"},
				"up": {"uv": [1.5, 1.5, 1.25, 1.25], "texture": "#0"},
				"down": {"uv": [1.75, 1.25, 1.5, 1.5], "texture": "#0"}
			}
		},
		{
			"from": [4.40725, 15.35073, 5.3],
			"to": [5.40725, 16.35073, 6.3],
			"rotation": {"angle": -45, "axis": "z", "origin": [4.90725, 15.85073, 5.8]},
			"faces": {
				"north": {"uv": [3.5, 0.75, 3.75, 1], "texture": "#0"},
				"east": {"uv": [3.25, 0.75, 3.5, 1], "texture": "#0"},
				"south": {"uv": [4, 0.75, 4.25, 1], "texture": "#0"},
				"west": {"uv": [3.75, 0.75, 4, 1], "texture": "#0"},
				"up": {"uv": [3.75, 0.75, 3.5, 0.5], "texture": "#0"},
				"down": {"uv": [4, 0.5, 3.75, 0.75], "texture": "#0"}
			}
		},
		{
			"from": [4.03653, 14.79733, 5.2],
			"to": [5.03653, 15.79733, 6.2],
			"rotation": {"angle": 0, "axis": "y", "origin": [4.53653, 15.29733, 5.7]},
			"faces": {
				"north": {"uv": [3.5, 1.25, 3.75, 1.5], "texture": "#0"},
				"east": {"uv": [3.25, 1.25, 3.5, 1.5], "texture": "#0"},
				"south": {"uv": [4, 1.25, 4.25, 1.5], "texture": "#0"},
				"west": {"uv": [3.75, 1.25, 4, 1.5], "texture": "#0"},
				"up": {"uv": [3.75, 1.25, 3.5, 1], "texture": "#0"},
				"down": {"uv": [4, 1, 3.75, 1.25], "texture": "#0"}
			}
		}
	]
}